pyprojectcheck/__init__.py
pyprojectcheck/checker.py
pyprojectcheck_rj-1.0.0.dist-info/METADATA
pyprojectcheck_rj-1.0.0.dist-info/WHEEL
pyprojectcheck_rj-1.0.0.dist-info/entry_points.txt
pyprojectcheck_rj-1.0.0.dist-info/RECORD
