Metadata-Version: 2.4
Name: pyprojectcheck-rj
Version: 1.0.0
Summary: Validate pyproject.toml files
Project-URL: Homepage, https://github.com/RedJohnx/pypi_warehouse
Project-URL: Repository, https://github.com/RedJohnx/pypi_warehouse/tree/main/packages/pyprojectcheck
Author-email: RedJohnx <redjohnx@example.com>
License-Expression: MIT
Keywords: linter,packaging,pyproject,toml,validation
Classifier: Development Status :: 5 - Production/Stable
Classifier: Intended Audience :: Developers
Classifier: License :: OSI Approved :: MIT License
Classifier: Programming Language :: Python :: 3
Classifier: Programming Language :: Python :: 3.8
Classifier: Programming Language :: Python :: 3.9
Classifier: Programming Language :: Python :: 3.10
Classifier: Programming Language :: Python :: 3.11
Classifier: Programming Language :: Python :: 3.12
Classifier: Topic :: Software Development :: Quality Assurance
Requires-Python: >=3.8
Requires-Dist: tomli>=2.0.0; python_version < '3.11'
